kwgis/__init__.py
kwgis/exceptions.py
kwgis/demo/__init__.py
kwgis/demo/demo_region.py
kwgis/demo/dummy_demodata.py
kwgis/demo/landsat_demodata.py
kwgis/demo/nitf_demodata.py
kwgis/demo/sentinel2_demodata.py
kwgis/demo/stac_demo.py
kwgis/demo/metrics_demo/__init__.py
kwgis/demo/metrics_demo/demo_rendering.py
kwgis/demo/metrics_demo/demo_truth.py
kwgis/demo/metrics_demo/demo_utils.py
kwgis/demo/metrics_demo/generate_demodata.py
kwgis/demo/metrics_demo/site_perterbing.py
kwgis/gis/__init__.py
kwgis/gis/digital_globe.py
kwgis/gis/elevation.py
kwgis/gis/geotiff.py
kwgis/gis/spatial_reference.py
kwgis/gis/sensors/__init__.py
kwgis/gis/sensors/sentinel2.py
kwgis/rc/__init__.py
kwgis/rc/registry.py
kwgis/rc/requirements/__init__.py
kwgis/rc/requirements/docs.txt
kwgis/rc/requirements/gdal.txt
kwgis/rc/requirements/graphics.txt
kwgis/rc/requirements/headless.txt
kwgis/rc/requirements/linting.txt
kwgis/rc/requirements/optional.txt
kwgis/rc/requirements/runtime.txt
kwgis/rc/requirements/tests.txt
kwgis/stac/__init__.py
kwgis/stac/stac_search_builder.py
kwgis/stac/util_stac.py
kwgis/utils/__init__.py
kwgis/utils/util_bands.py
kwgis/utils/util_gdal.py
kwgis/utils/util_gis.py
kwgis/utils/util_retry.py
kwgis/utils/util_rgdc.py
kwgis/utils/util_sunlight.py
requirements/__init__.py
requirements/docs.txt
requirements/gdal.txt
requirements/graphics.txt
requirements/headless.txt
requirements/linting.txt
requirements/optional.txt
requirements/runtime.txt
requirements/tests.txt
kwgis-0.1.1.dist-info/METADATA
kwgis-0.1.1.dist-info/WHEEL
kwgis-0.1.1.dist-info/top_level.txt
kwgis-0.1.1.dist-info/RECORD
